{
  "0": {
    "name": "MrsSpelling",
    "timeOffset": 8000,
    "url": "atp:/recordings/0805-MrsSpelling.hfr",
    "ready": false,
    "startTrim": 0,
    "endTrim": 77650
  },
  "2": {
    "name": "Leah",
    "timeOffset": 1000,
    "url": "atp:/recordings/0805-Leah.hfr",
    "ready": false,
    "startTrim": 0,
    "endTrim": 84650
  },
  "3": {
    "name": "David",
    "timeOffset": 1000,
    "url": "atp:/recordings/0805-David.hfr",
    "ready": false,
    "startTrim": 0,
    "endTrim": 0
  },
  "4": {
    "name": "HairPlane",
    "timeOffset": 1000,
    "url": "atp:/recordings/0805-HairPlane.hfr",
    "ready": false,
    "startTrim": 0,
    "endTrim": 0
  }
}